hyperboost/__init__.py
hyperboost/optimizers/__init__.py
hyperboost/optimizers/bayesian.py
hyperboost/optimizers/evo.py
hyperboost/parallel/__init__.py
hyperboost/parallel/evaluate.py
hyperboost/space/__init__.py
hyperboost/space/search.py
hyperboost/space/types.py
hyperboost/utils/__init__.py
hyperboost/utils/logger.py
hyperboost/utils/persistence.py
hyperboost/utils/visual.py
hyperboost-0.1.1.dist-info/licenses/LICENSE
hyperboost-0.1.1.dist-info/METADATA
hyperboost-0.1.1.dist-info/WHEEL
hyperboost-0.1.1.dist-info/top_level.txt
hyperboost-0.1.1.dist-info/RECORD
